snappyzones/__init__.py
snappyzones/__main__.py
snappyzones/builder.py
snappyzones/cmd_reader.py
snappyzones/help_menu.py
snappyzones/process.py
snappyzones/service.py
snappyzones/snap.py
snappyzones/zoning.py
snappyzones/conf/__init__.py
snappyzones/conf/settings.py
snappyzones/conf/zones.json
snappyzones-0.0.4.dist-info/LICENSE.txt
snappyzones-0.0.4.dist-info/METADATA
snappyzones-0.0.4.dist-info/WHEEL
snappyzones-0.0.4.dist-info/entry_points.txt
snappyzones-0.0.4.dist-info/top_level.txt
snappyzones-0.0.4.dist-info/RECORD
