Metadata-Version: 2.1
Name: snappyzones
Version: 0.0.4
Summary: a Linux window manager based on Microsoft's FancyZones
Home-page: https://github.com/1mikegrn/snappyzones
Author: Michael Green
Author-email: 1mikegrn@gmail.com
License: UNKNOWN
Platform: UNKNOWN
Classifier: Development Status :: 3 - Alpha
Classifier: License :: OSI Approved :: GNU Lesser General Public License v3 (LGPLv3)
Classifier: Operating System :: POSIX :: Linux
Classifier: Programming Language :: Python :: 3
Classifier: Programming Language :: Python :: 3.8
Classifier: Programming Language :: Python :: 3.9
Classifier: Topic :: Software Development :: Libraries :: Python Modules
Requires-Python: >=3.8
Requires-Dist: python3-xlib (==0.15)
